dataorigin/__init__.py
dataorigin/google_sheets.py
dataorigin-1.6.4.dist-info/licenses/LICENSE
dataorigin-1.6.4.dist-info/METADATA
dataorigin-1.6.4.dist-info/WHEEL
dataorigin-1.6.4.dist-info/top_level.txt
dataorigin-1.6.4.dist-info/RECORD
